factorymind/__init__.py
factorymind/data_loader.py
factorymind/exceptions.py
factorymind/timing_utils.py
factorymind-0.1.3.dist-info/LICENSE
factorymind-0.1.3.dist-info/WHEEL
factorymind-0.1.3.dist-info/METADATA
factorymind-0.1.3.dist-info/RECORD
